nexus/__init__.py
nexus/benchmarks/__init__.py
nexus/benchmarks/model_benchmarks.py
nexus/benchmarks/performance_metrics.py
nexus/benchmarks/standard_benchmarks.py
nexus/components/__init__.py
nexus/components/normalization.py
nexus/components/attention/__init__.py
nexus/components/attention/base.py
nexus/components/attention/base_attention.py
nexus/components/attention/cross_attention.py
nexus/components/attention/efficient_attention.py
nexus/components/attention/flash_attention.py
nexus/components/attention/multi_head_attention.py
nexus/components/attention/rotary_embedding.py
nexus/components/attention/self_attention.py
nexus/components/attention/spatial_attention.py
nexus/components/attention/unified_attention.py
nexus/components/blocks/__init__.py
nexus/components/blocks/residual.py
nexus/components/blocks/transformer.py
nexus/core/__init__.py
nexus/core/base.py
nexus/core/config.py
nexus/core/initialization.py
nexus/core/registry.py
nexus/data/__init__.py
nexus/data/augmentation.py
nexus/data/cache.py
nexus/data/dataloader.py
nexus/data/dataset.py
nexus/data/inputs.py
nexus/data/processors.py
nexus/data/replay_buffer.py
nexus/data/streaming.py
nexus/data/text_processor.py
nexus/data/tokenizer.py
nexus/data/transforms.py
nexus/models/__init__.py
nexus/models/agents/__init__.py
nexus/models/agents/agent_town.py
nexus/models/agents/environment.py
nexus/models/agents/interaction.py
nexus/models/cv/__init__.py
nexus/models/cv/atom_tracker.py
nexus/models/cv/compact_cnn.py
nexus/models/cv/detr.py
nexus/models/cv/efficient_net.py
nexus/models/cv/swin_transformer.py
nexus/models/cv/vit.py
nexus/models/cv/city_reconstruction/__init__.py
nexus/models/cv/city_reconstruction/mesh_generator.py
nexus/models/cv/city_reconstruction/point_cloud.py
nexus/models/cv/city_reconstruction/reconstruction.py
nexus/models/cv/city_reconstruction/texture_mapper.py
nexus/models/cv/mask_rcnn/__init__.py
nexus/models/cv/mask_rcnn/backbone.py
nexus/models/cv/mask_rcnn/mask_rcnn.py
nexus_deep_learning-0.1.0.dist-info/METADATA
nexus_deep_learning-0.1.0.dist-info/WHEEL
nexus_deep_learning-0.1.0.dist-info/top_level.txt
nexus_deep_learning-0.1.0.dist-info/RECORD
