Metadata-Version: 2.1
Name: nexus-deep-learning
Version: 0.1.0
Summary: A modular deep learning library for implementing AI research papers
Home-page: https://github.com/yourusername/nexus
Author: Your Name
Author-email: your.email@example.com
Classifier: Development Status :: 3 - Alpha
Classifier: Intended Audience :: Science/Research
Classifier: License :: OSI Approved :: MIT License
Classifier: Programming Language :: Python :: 3.7
Classifier: Programming Language :: Python :: 3.8
Classifier: Programming Language :: Python :: 3.9
Requires-Python: >=3.7
Requires-Dist: torch>=1.9.0
Requires-Dist: torchvision>=0.10.0
Requires-Dist: numpy>=1.19.0
Requires-Dist: pynvml>=11.0.0
Requires-Dist: PyYAML>=5.4.1
Requires-Dist: tqdm>=4.62.0
Requires-Dist: pillow>=8.3.0
Requires-Dist: scikit-learn>=0.24.0
Requires-Dist: faiss-cpu>=1.7.0
Requires-Dist: datasets>=2.14.0
